LICENSE
MANIFEST.in
README.rst
setup.py
django_gerencianet.egg-info/PKG-INFO
django_gerencianet.egg-info/SOURCES.txt
django_gerencianet.egg-info/dependency_links.txt
django_gerencianet.egg-info/requires.txt
django_gerencianet.egg-info/top_level.txt
gerencianet/__init__.py
gerencianet/admin.py
gerencianet/constants.py
gerencianet/entities.py
gerencianet/exceptions.py
gerencianet/gateway.py
gerencianet/models.py
gerencianet/repository.py
gerencianet/services.py
gerencianet/tests.py
gerencianet/urls.py
gerencianet/views.py
gerencianet/migrations/0001_initial.py
gerencianet/migrations/0001_initial.pyc
gerencianet/migrations/0002_auto_20151019_1639.py
gerencianet/migrations/__init__.py
gerencianet/migrations/__init__.pyc