Metadata-Version: 1.1
Name: django-gerencianet
Version: 0.1.4
Summary: Uma aplicação django para comunicar com o gateway de pagamento Gerencianet
Home-page: https://github.com/sidneycarlos65/django-gerencianet
Author: Sidney Machado
Author-email: sidney.machado@starlinetecnologia.com.br
License: BSD License
Platform: UNKNOWN
Classifier: Environment :: Web Environment
Classifier: Framework :: Django
Classifier: Intended Audience :: Developers
Classifier: License :: OSI Approved :: BSD License
Classifier: Operating System :: OS Independent
Classifier: Programming Language :: Python
Classifier: Programming Language :: Python :: 2
